{
    "title": "Title Text",
    "startPre": "super epic example pretext",
    "credit": "Me, Myself & I",
    "preText": [
        "background on question one",
        "background on question two",
        "background on question three",
        "background on question four"
    ],
    "questions": [
        "Question number one?",
        "Question number two?",
        "Question number three?",
        "Question number four?"
    ],
    "options": [
        [
            "option 1",
            "option 2",
            "option 3",
            "option 4"
        ],
        [
            "option 1",
            "option 2",
            "option 3",
            "option 4"
        ],
        [
            "option 1",
            "option 2",
            "option 3",
            "option 4"
        ],
        [
            "option 1",
            "option 2",
            "option 3",
            "option 4"
        ]
    ],
    "answers": [
        1,
        2,
        3,
        4
    ]
}